pyblisher/Bucket.py
pyblisher/Project.py
pyblisher/Settings.py
pyblisher/Source.py
pyblisher/Task.py
pyblisher/User.py
pyblisher/__init__.py
pyblisher/auth.py
pyblisher/client.py
pyblisher/core.py
pyblisher/exceptions.py
pyblisher/helpers.py
pyblisher/types.py
pyblisher-0.8.4.dist-info/METADATA
pyblisher-0.8.4.dist-info/WHEEL
pyblisher-0.8.4.dist-info/licenses/LICENSE
pyblisher-0.8.4.dist-info/RECORD
