Metadata-Version: 2.4
Name: pyblisher
Version: 0.8.4
Summary: A simple Python SDK for the VCPublish API by VCS.
Project-URL: Repository, https://github.com/rostock/pyblisher
License: MIT License
License-File: LICENSE
Requires-Python: >=3.11
Requires-Dist: dacite>=1.8.1
Requires-Dist: httpx>=0.28.1
Requires-Dist: tqdm>=4.67.1
